LICENSE
MANIFEST.in
README.md
pyproject.toml
setup.cfg
setup.py
versioneer.py
./ghost_writer/__init__.py
./ghost_writer/_version.py
./ghost_writer/ghost_writer.py
./ghost_writer/scriptify.py
./ghost_writer/data/generated_test_script.py
./ghost_writer/data/script.py
./ghost_writer/scripts/__init__.py
./ghost_writer/scripts/cmd_line.py
./ghost_writer/test/conftest.py
./ghost_writer/test/test_basic.py
./ghost_writer/utils/__init__.py
./ghost_writer/utils/configuration.py
./ghost_writer/utils/logging.py
./ghost_writer/utils/package_data.py
ghost_writer/_version.py
ghost_writer/data/generated_test_script.py
ghost_writer/data/log_theme.ini
ghost_writer/data/script.py
pyghost_writer.egg-info/PKG-INFO
pyghost_writer.egg-info/SOURCES.txt
pyghost_writer.egg-info/dependency_links.txt
pyghost_writer.egg-info/entry_points.txt
pyghost_writer.egg-info/requires.txt
pyghost_writer.egg-info/top_level.txt