Metadata-Version: 2.1
Name: pyghost-writer
Version: 0.1.2
Summary: A simple code generator
Home-page: https://github.com/grburgess/ghost_writer
Author: J. Michael Burgess
Author-email: jburgess@mpe.mpg.de
License: GPL-2+
Project-URL: Bug Tracker, https://github.com/grburgess/ghost_writer/issues
Project-URL: Source Code, https://github.com/grburgess/ghost_writer
Platform: UNKNOWN
Classifier: Development Status :: 2 - Pre-Alpha
Classifier: Environment :: Console
Classifier: Intended Audience :: Science/Research
Classifier: License :: OSI Approved :: GNU General Public License v2 or later (GPLv2+)
Classifier: Operating System :: POSIX
Classifier: Programming Language :: Python :: 3.7
Classifier: Programming Language :: Python :: 3.8
Classifier: Programming Language :: Python :: 3.9
Classifier: Topic :: Scientific/Engineering :: Physics
